pygraff/__init__.py
pygraff/generator.py
pygraff/settings.py
pygraff-1.2.1.data/scripts/graff
pygraff-1.2.1.dist-info/LICENSE
pygraff-1.2.1.dist-info/METADATA
pygraff-1.2.1.dist-info/WHEEL
pygraff-1.2.1.dist-info/top_level.txt
pygraff-1.2.1.dist-info/RECORD
