Metadata-Version: 2.1
Name: pygraff
Version: 1.2.1
Summary: An overkill blog previews generator
Home-page: https://github.com/cryptolake/Graff
Author: Dhia
Author-email: dhiadah@gmail.com
License: MIT
Platform: UNKNOWN
Classifier: License :: OSI Approved :: MIT License
Classifier: Programming Language :: Python
Classifier: Programming Language :: Python :: 3
Classifier: Programming Language :: Python :: 3.7
Classifier: Programming Language :: Python :: Implementation :: CPython
Classifier: Programming Language :: Python :: Implementation :: PyPy
Requires-Python: >=3.7.0
Requires-Dist: beautifulsoup4
